README.md
setup.cfg
setup.py
dariah_topics/__init__.py
dariah_topics/evaluation.py
dariah_topics/modeling.py
dariah_topics/postprocessing.py
dariah_topics/preprocessing.py
dariah_topics/utils.py
dariah_topics/visualization.py
dariah_topics.egg-info/PKG-INFO
dariah_topics.egg-info/SOURCES.txt
dariah_topics.egg-info/dependency_links.txt
dariah_topics.egg-info/requires.txt
dariah_topics.egg-info/top_level.txt
test/test_fuzzy_segmenting.py